pdfcrowd.py
pdfcrowd-6.5.3.data/scripts/html2image
pdfcrowd-6.5.3.data/scripts/html2pdf
pdfcrowd-6.5.3.data/scripts/image2image
pdfcrowd-6.5.3.data/scripts/image2pdf
pdfcrowd-6.5.3.data/scripts/pdf2html
pdfcrowd-6.5.3.data/scripts/pdf2image
pdfcrowd-6.5.3.data/scripts/pdf2pdf
pdfcrowd-6.5.3.data/scripts/pdf2text
pdfcrowd-6.5.3.dist-info/LICENSE
pdfcrowd-6.5.3.dist-info/METADATA
pdfcrowd-6.5.3.dist-info/WHEEL
pdfcrowd-6.5.3.dist-info/top_level.txt
pdfcrowd-6.5.3.dist-info/RECORD
