Metadata-Version: 2.1
Name: pdfcrowd
Version: 6.5.3
Summary: A client library for the PDFCrowd API.
Home-page: https://pdfcrowd.com/api/
Author: PDFCrowd Team
Author-email: support@pdfcrowd.com
License: License :: OSI Approved :: MIT License
Classifier: License :: OSI Approved :: MIT License
Classifier: Operating System :: MacOS
Classifier: Operating System :: Microsoft
Classifier: Operating System :: POSIX
Classifier: Operating System :: Unix
Classifier: Intended Audience :: Developers
Classifier: Topic :: Software Development :: Libraries
License-File: LICENSE
